[
{"año":1996,"ent":"Aguascalientes","pob":939507}
,
{"año":1996,"ent":"Baja California","pob":2224286}
,
{"año":1996,"ent":"Baja California Sur","pob":413575}
,
{"año":1996,"ent":"Campeche","pob":644818}
,
{"año":1996,"ent":"Chiapas","pob":3819739}
,
{"año":1996,"ent":"Chihuahua","pob":2753282}
,
{"año":1996,"ent":"Coahuila","pob":2237025}
,
{"año":1996,"ent":"Colima","pob":524947}
,
{"año":1996,"ent":"Distrito Federal","pob":8875396}
,
{"año":1996,"ent":"Durango","pob":1462829}
,
{"año":1996,"ent":"Guanajuato","pob":4990233}
,
{"año":1996,"ent":"Guerrero","pob":3170156}
,
{"año":1996,"ent":"Hidalgo","pob":2326530}
,
{"año":1996,"ent":"Jalisco","pob":6270725}
,
{"año":1996,"ent":"México","pob":11876981}
,
{"año":1996,"ent":"Michoacán","pob":4140754}
,
{"año":1996,"ent":"Morelos","pob":1533870}
,
{"año":1996,"ent":"Nayarit","pob":910767}
,
{"año":1996,"ent":"Nuevo León","pob":3663689}
,
{"año":1996,"ent":"Oaxaca","pob":3566944}
,
{"año":1996,"ent":"Puebla","pob":4969986}
,
{"año":1996,"ent":"Querétaro","pob":1434671}
,
{"año":1996,"ent":"Quintana Roo","pob":788218}
,
{"año":1996,"ent":"San Luis Potosí","pob":2336411}
,
{"año":1996,"ent":"Sinaloa","pob":2420265}
,
{"año":1996,"ent":"Sonora","pob":2117226}
,
{"año":1996,"ent":"Tabasco","pob":1849738}
,
{"año":1996,"ent":"Tamaulipas","pob":2560332}
,
{"año":1996,"ent":"Tlaxcala","pob":934238}
,
{"año":1996,"ent":"Veracruz","pob":7075631}
,
{"año":1996,"ent":"Yucatán","pob":1614983}
,
{"año":1996,"ent":"Zacatecas","pob":1428912}

]